{"data":{"wordpressPage":{"title":"Geo Block","content":"<h2>Thank you for your interest</h2>\n<p>\n        Unfortunately Chumba Casino is not available in this country.</p>\n<p>        &#8211; Team VGW\n    </p>\n","yoast_meta":{"yoast_wpseo_title":"Geo Block - Chumba Casino","yoast_wpseo_metadesc":"","yoast_wpseo_canonical":"http://localhost:8000/geo-block/","yoast_wpseo_facebook_title":"","yoast_wpseo_facebook_description":"","yoast_wpseo_facebook_type":"page","yoast_wpseo_facebook_image":"","yoast_wpseo_twitter_title":"","yoast_wpseo_twitter_description":"","yoast_wpseo_twitter_image":"","yoast_wpseo_social_url":"http://localhost:8000/geo-block/","yoast_wpseo_company_or_person":"","yoast_wpseo_person_name":"","yoast_wpseo_company_name":"","yoast_wpseo_company_logo":"","yoast_wpseo_website_name":""},"acf":null}},"pageContext":{"isCreatedByStatefulCreatePages":false,"id":"a809635f-ea6f-5a0e-9585-d434c848dce7"}}